netatmo_geopy/__init__.py
netatmo_geopy/auth.py
netatmo_geopy/cli.py
netatmo_geopy/core.py
netatmo_geopy/settings.py
netatmo_geopy/utils.py
netatmo_geopy-0.1.0.dist-info/entry_points.txt
netatmo_geopy-0.1.0.dist-info/LICENSE
netatmo_geopy-0.1.0.dist-info/WHEEL
netatmo_geopy-0.1.0.dist-info/METADATA
netatmo_geopy-0.1.0.dist-info/RECORD
